{
    "app-id": "com.github.melix99.telegrand.Devel",
    "runtime": "org.gnome.Platform",
    "runtime-version": "43",
    "sdk": "org.gnome.Sdk",
    "sdk-extensions": [
        "org.freedesktop.Sdk.Extension.rust-stable",
        "org.freedesktop.Sdk.Extension.llvm14"
    ],
    "command": "telegrand",
    "finish-args": [
        "--socket=fallback-x11",
        "--socket=wayland",
        "--share=network",
        "--share=ipc",
        "--device=dri",
        "--env=G_MESSAGES_DEBUG=none",
        "--env=RUST_BACKTRACE=1"
    ],
    "build-options": {
        "append-path": "/usr/lib/sdk/rust-stable/bin:/usr/lib/sdk/llvm14/bin",
        "env": {
            "CARGO_TARGET_X86_64_UNKNOWN_LINUX_GNU_LINKER": "clang",
            "CARGO_TARGET_X86_64_UNKNOWN_LINUX_GNU_RUSTFLAGS": "-C link-arg=-fuse-ld=/usr/lib/sdk/rust-stable/bin/mold",
            "CARGO_TARGET_AARCH64_UNKNOWN_LINUX_GNU_LINKER": "clang",
            "CARGO_TARGET_AARCH64_UNKNOWN_LINUX_GNU_RUSTFLAGS": "-C link-arg=-fuse-ld=/usr/lib/sdk/rust-stable/bin/mold"
        },
        "build-args": [
            "--share=network"
        ]
    },
    "cleanup": [
        "/include",
        "/lib/cmake",
        "/lib/pkgconfig",
        "*.a"
    ],
    "modules": [
        {
            "name": "rlottie",
            "buildsystem": "meson",
            "config-opts": ["-Dwerror=false"],
            "sources": [
                {
                    "type": "git",
                    "url": "https://github.com/melix99/rlottie",
                    "branch": "fix-build"
                }
            ]
        },
        {
            "name": "gtk",
            "buildsystem": "meson",
            "config-opts": [
                "-Dbuild-tests=false",
                "-Ddemos=false",
                "-Dbuild-examples=false",
                "-Dintrospection=disabled"
            ],
            "sources": [
                {
                    "type": "git",
                    "url": "https://gitlab.gnome.org/GNOME/gtk.git",
                    "tag": "4.8.2"
                },
                {
                    "type": "patch",
                    "path": "gtk-reversed-list.patch"
                }
            ]
        },
        {
            "name": "tdlib-prebuilt",
            "only-arches": [
                "x86_64",
                "aarch64"
            ],
            "buildsystem": "simple",
            "build-commands": [
                "install -d /app/lib/pkgconfig",
                "install -D libtdjson.so.* /app/lib",
                "ln -sf /app/lib/libtdjson.so.* /app/lib/libtdjson.so",
                "install -D pkgconfig/* /app/lib/pkgconfig"
            ],
            "sources": [
                {
                    "only-arches": [
                        "x86_64"
                    ],
                    "type": "archive",
                    "url": "https://github.com/melix99/tdjson-ci/releases/download/1.8.10/tdjson-x86_64.zip",
                    "sha256": "5b46b76d090e544605970d1d7fb44609959be4992efff1d6afe2d7b6d24b6b9f",
                    "strip-components": 0
                },
                {
                    "only-arches": [
                        "aarch64"
                    ],
                    "type": "archive",
                    "url": "https://github.com/melix99/tdjson-ci/releases/download/1.8.10/tdjson-aarch64.zip",
                    "sha256": "19efbcf8ed5b161427f4d04da02a50331b5f31b50d4b8e61f0af49a8f30f322e",
                    "strip-components": 0
                }
            ]
        },
        {
            "name": "tdlib",
            "skip-arches": [
                "x86_64",
                "aarch64"
            ],
            "buildsystem": "cmake-ninja",
            "builddir": true,
            "config-opts": [
                "-DCMAKE_BUILD_TYPE=Release"
            ],
            "sources": [
                {
                    "type": "git",
                    "url": "https://github.com/tdlib/td.git",
                    "commit": "93c42f6d7c1209937431469f80427d48907f1b8d"
                }
            ]
        },
        {
            "name": "telegrand",
            "buildsystem": "meson",
            "run-tests": true,
            "config-opts": [
                "-Dprofile=development"
            ],
            "sources": [
                {
                    "type": "dir",
                    "path": "../"
                }
            ]
        }
    ]
}
